watchtower/__init__.py
watchtower/subscription.py
watchtower/bch/__init__.py
watchtower/bch/bch.py
watchtower/slp/__init__.py
watchtower/slp/type1.py
watchtower/wallet/__init__.py
watchtower/wallet/wallet.py
watchtower_cash_py-0.1.7.dist-info/LICENSE
watchtower_cash_py-0.1.7.dist-info/METADATA
watchtower_cash_py-0.1.7.dist-info/WHEEL
watchtower_cash_py-0.1.7.dist-info/dependency_links.txt
watchtower_cash_py-0.1.7.dist-info/top_level.txt
watchtower_cash_py-0.1.7.dist-info/RECORD
