Metadata-Version: 2.1
Name: watchtower-cash-py
Version: 0.1.7
Summary: Library for building Python applications that integrate with Watchtower.cash
Home-page: https://github.com/paytaca/watchtower-cash-py
Author: Joemar Taganna
Author-email: joemar@paytaca.com
License: MIT
Platform: UNKNOWN
Classifier: Development Status :: 3 - Alpha
Classifier: Intended Audience :: Developers
Classifier: License :: OSI Approved :: MIT License
Classifier: Operating System :: MacOS :: MacOS X
Classifier: Operating System :: POSIX :: Linux
Classifier: Programming Language :: Python :: 3.8
Requires-Dist: requests (>=2.22.0)
Requires-Dist: bitcash
